wordcloud_mapper/__init__.py
wordcloud_mapper/calc_tfidf.py
wordcloud_mapper/load_companies.py
wordcloud_mapper/resize_map.py
wordcloud_mapper/wordcloud_map.py
wordcloud_mapper/data/__init__.py
wordcloud_mapper/data/companies_DEU.csv
wordcloud_mapper/data/companies_ITA.csv
wordcloud_mapper-0.2.0.dist-info/LICENSE
wordcloud_mapper-0.2.0.dist-info/METADATA
wordcloud_mapper-0.2.0.dist-info/WHEEL
wordcloud_mapper-0.2.0.dist-info/top_level.txt
wordcloud_mapper-0.2.0.dist-info/RECORD
