Metadata-Version: 2.1
Name: wordcloud-mapper
Version: 0.2.0
Summary: A package for creating wordcloud maps in Python.
Home-page: https://github.com/GabZech/wordcloud_mapper
Author: Gabriel da Silva Zech
Author-email: g.dev@posteo.net
License: GNU General Public License v3
Project-URL: Documentation, https://gabzech.github.io/wordcloud_mapper
Keywords: wordcloud_mapper
Classifier: Development Status :: 4 - Beta
Classifier: Intended Audience :: Developers
Classifier: License :: OSI Approved :: GNU General Public License v3 (GPLv3)
Classifier: Natural Language :: English
Classifier: Programming Language :: Python :: 3
Classifier: Programming Language :: Python :: 3.8
Classifier: Programming Language :: Python :: 3.9
Classifier: Programming Language :: Python :: 3.10
Requires-Python: >=3.8
License-File: LICENSE
Requires-Dist: pyshp (>=2.3)
Requires-Dist: wordcloud (>=1.7)
Requires-Dist: numpy (>=1.23)
Requires-Dist: matplotlib (>=3.5)
Requires-Dist: descartes (>=1.1)
Requires-Dist: pandas (>=1.0)
